{
    "TestAgentProtocol_CreateAgentTask": true,
    "TestWriteFile": true,
    "TestAgentProtocol_ListAgentTasksIds": true,
    "TestSearch": true,
    "TestReadFile": true,
    "TestAgentProtocol_GetAgentTask": true,
    "TestAgentProtocol_ExecuteAgentTaskStep": true,
    "TestAgentProtocol_ListAgentTaskSteps": true,
    "TestPlanCreation": true,
    "TestRememberGoal_Simple": true,
    "TestRememberGoal_Hard": true,
    "TestDebugSimpleTypoWithGuidance": true,
    "TestPasswordGenerator_Easy": true,
    "TestReturnCode_Simple": true,
    "TestUrlShortener": true,
    "TestDebugSimpleTypoWithoutGuidance": true,
    "TestWritingCLI_FileOrganizer": true,
    "TestReturnCode_Write": true,
    "TestDebugMultipleTypo": true,
    "TestWebApp_ListAnimals": true,
    "TestFunctionCodeGeneration": true,
    "TestReturnCode_Modify": true,
    "TestThreeSum": true,
    "TestReturnCode_Tests": true,
    "TestAdaptSimpleTypoWithGuidance": true,
    "TestBasicMemory": true,
    "TestRememberGoal_Advanced": true,
    "TestRememberMultipleIds": true,
    "TestRememberMultipleIdsWithNoise": true,
    "TestRevenueRetrieval_1.0": true,
    "TestAdaptTeslaRevenue": true,
    "TestGetEthereumGasPrice": true,
    "TestBasicRetrieval": true,
    "TestWrite5FilesWithArray": true,
    "TestRevenueRetrieval": true,
    "TestRevenueRetrieval_1.2": true,
    "TestRevenueRetrieval_1.1": true,
    "TestAdaptLink": true,
    "TestRememberGoal_Medium": true,
    "TestWrite6Files": true,
    "TestRetrieval3": true,
    "TestRememberMultiplePhrasesWithNoise": true
}